iobl/__init__.py
iobl/__main__.py
iobl/parser.py
iobl/protocol.py
iobl-0.0.4.dist-info/DESCRIPTION.rst
iobl-0.0.4.dist-info/METADATA
iobl-0.0.4.dist-info/RECORD
iobl-0.0.4.dist-info/WHEEL
iobl-0.0.4.dist-info/entry_points.txt
iobl-0.0.4.dist-info/metadata.json
iobl-0.0.4.dist-info/top_level.txt
