Metadata-Version: 2.0
Name: iobl
Version: 0.0.4
Summary: Library and CLI tools for interacting with IOBL PLC gateway.
Home-page: https://github.com/boblegal31/iobl
Author: François LEGAL
Author-email: devel@thom.fr.eu.org
License: MIT
Keywords: iobl plc legrand domotica
Platform: UNKNOWN
Classifier: Development Status :: 3 - Alpha
Classifier: Intended Audience :: Developers
Classifier: License :: OSI Approved :: MIT License
Classifier: Programming Language :: Python :: 3.4
Classifier: Programming Language :: Python :: 3.5
Requires-Dist: docopt
Requires-Dist: pyserial-asyncio
Requires-Dist: typing
